callcenterdim/Dimensionamento.py
callcenterdim/__init__.py
CallCenterDim-0.0.3.dist-info/LICENSE
CallCenterDim-0.0.3.dist-info/METADATA
CallCenterDim-0.0.3.dist-info/WHEEL
CallCenterDim-0.0.3.dist-info/top_level.txt
CallCenterDim-0.0.3.dist-info/RECORD
